surrealist/__init__.py
surrealist/enums.py
surrealist/errors.py
surrealist/record_id.py
surrealist/result.py
surrealist/surreal.py
surrealist/utils.py
surrealist/clients/__init__.py
surrealist/clients/http_client.py
surrealist/clients/ws_client.py
surrealist/connections/__init__.py
surrealist/connections/connection.py
surrealist/connections/http_connection.py
surrealist/connections/pool.py
surrealist/connections/ws_connection.py
surrealist/ql/__init__.py
surrealist/ql/database.py
surrealist/ql/pool_database.py
surrealist/ql/table.py
surrealist/ql/statements/__init__.py
surrealist/ql/statements/access.py
surrealist/ql/statements/access_statements.py
surrealist/ql/statements/alter.py
surrealist/ql/statements/common_statements.py
surrealist/ql/statements/create.py
surrealist/ql/statements/create_statements.py
surrealist/ql/statements/define.py
surrealist/ql/statements/define_access.py
surrealist/ql/statements/define_analyzer.py
surrealist/ql/statements/define_config.py
surrealist/ql/statements/define_field.py
surrealist/ql/statements/define_index_statements.py
surrealist/ql/statements/define_user.py
surrealist/ql/statements/delete.py
surrealist/ql/statements/insert.py
surrealist/ql/statements/insert_statements.py
surrealist/ql/statements/live.py
surrealist/ql/statements/live_statements.py
surrealist/ql/statements/permissions.py
surrealist/ql/statements/rebuild_index.py
surrealist/ql/statements/relate.py
surrealist/ql/statements/remove.py
surrealist/ql/statements/returns.py
surrealist/ql/statements/select.py
surrealist/ql/statements/select_statements.py
surrealist/ql/statements/show.py
surrealist/ql/statements/simple_statements.py
surrealist/ql/statements/statement.py
surrealist/ql/statements/transaction.py
surrealist/ql/statements/update.py
surrealist/ql/statements/update_statements.py
surrealist/ql/statements/upsert.py
surrealist/ql/statements/utils.py
surrealist-1.1.2.dist-info/LICENSE
surrealist-1.1.2.dist-info/METADATA
surrealist-1.1.2.dist-info/WHEEL
surrealist-1.1.2.dist-info/top_level.txt
surrealist-1.1.2.dist-info/RECORD
