Metadata-Version: 2.1
Name: surrealist
Version: 1.1.2
Summary: Python client for SurrealDB, latest SurrealDB version compatible, all features supported
Author-email: kotolex <farofwell@gmail.com>
License: Copyright (c) 2018 The Python Packaging Authority
Project-URL: Homepage, https://github.com/kotolex/surrealist
Keywords: surreal,python,Surreal,SurrealDB,surrealist,database,surrealdb,surrealdb.py
Classifier: License :: OSI Approved :: MIT License
Classifier: Intended Audience :: Developers
Classifier: Intended Audience :: System Administrators
Classifier: Intended Audience :: Education
Classifier: Topic :: Software Development
Classifier: Topic :: Database
Classifier: Topic :: Software Development :: Libraries
Classifier: Development Status :: 5 - Production/Stable
Classifier: Operating System :: OS Independent
Classifier: Programming Language :: Python :: 3.8
Classifier: Programming Language :: Python :: 3.9
Classifier: Programming Language :: Python :: 3.10
Classifier: Programming Language :: Python :: 3.11
Classifier: Programming Language :: Python :: 3.12
Classifier: Programming Language :: Python :: 3.13
Requires-Python: >=3.8
License-File: LICENSE
Requires-Dist: websocket-client
